README.md
setup.py
pyBBarolo/BB_interface.py
pyBBarolo/BBarolo.tar.gz
pyBBarolo/__init__.py
pyBBarolo/_version.py
pyBBarolo/pyBBarolo.py
pyBBarolo/utils.py
pyBBarolo/wrapper.py
pyBBarolo.egg-info/PKG-INFO
pyBBarolo.egg-info/SOURCES.txt
pyBBarolo.egg-info/dependency_links.txt
pyBBarolo.egg-info/top_level.txt