Metadata-Version: 2.1
Name: pyBBarolo
Version: 1.3.0
Summary: a Python wrapper to BBarolo code
Home-page: https://github.com/editeodoro/Bbarolo
Download-URL: https://github.com/editeodoro/Bbarolo
Author: Enrico Di Teodoro
Author-email: enrico.diteodoro@gmail.com
Classifier: Development Status :: 3 - Alpha
Classifier: Programming Language :: Python
Classifier: License :: OSI Approved :: GNU General Public License v3 (GPLv3)
